README.rst
setup.cfg
setup.py
capybara/__init__.py
capybara/compat.py
capybara/dsl.py
capybara/exceptions.py
capybara/helpers.py
capybara/html.py
capybara/pytest_plugin.py
capybara/result.py
capybara/server.py
capybara/session.py
capybara/session_matchers.py
capybara/utils.py
capybara/version.py
capybara/window.py
capybara/driver/__init__.py
capybara/driver/base.py
capybara/driver/node.py
capybara/node/__init__.py
capybara/node/actions.py
capybara/node/base.py
capybara/node/document.py
capybara/node/document_matchers.py
capybara/node/element.py
capybara/node/finders.py
capybara/node/matchers.py
capybara/node/simple.py
capybara/queries/__init__.py
capybara/queries/ancestor_query.py
capybara/queries/base_query.py
capybara/queries/current_path_query.py
capybara/queries/selector_query.py
capybara/queries/sibling_query.py
capybara/queries/style_query.py
capybara/queries/text_query.py
capybara/queries/title_query.py
capybara/selector/__init__.py
capybara/selector/abstract_filter.py
capybara/selector/expression_filter.py
capybara/selector/filter_set.py
capybara/selector/node_filter.py
capybara/selector/selector.py
capybara/selenium/__init__.py
capybara/selenium/browser.py
capybara/selenium/driver.py
capybara/selenium/node.py
capybara/tests/__init__.py
capybara/tests/assertions.py
capybara/tests/collector.py
capybara/tests/compat.py
capybara/tests/conftest.py
capybara/tests/helpers.py
capybara/tests/pytest_plugin.py
capybara/tests/suite.py
capybara/tests/app/__init__.py
capybara/tests/app/static/jquery-ui.js
capybara/tests/app/static/jquery.js
capybara/tests/app/static/test.js
capybara/tests/app/templates/buttons.html
capybara/tests/app/templates/fieldsets.html
capybara/tests/app/templates/form.html
capybara/tests/app/templates/frame_child.html
capybara/tests/app/templates/frame_one.html
capybara/tests/app/templates/frame_parent.html
capybara/tests/app/templates/frame_two.html
capybara/tests/app/templates/header_links.html
capybara/tests/app/templates/host_links.html
capybara_py.egg-info/PKG-INFO
capybara_py.egg-info/SOURCES.txt
capybara_py.egg-info/dependency_links.txt
capybara_py.egg-info/requires.txt
capybara_py.egg-info/top_level.txt