Metadata-Version: 2.1
Name: capybara-py
Version: 0.1.6
Summary: Acceptance test framework for web applications
Home-page: https://github.com/elliterate/capybara.py
Author: Ian Lesperance
Author-email: ian@elliterate.com
License: MIT
Keywords: capybara
Platform: UNKNOWN
Classifier: Development Status :: 4 - Beta
Classifier: Intended Audience :: Developers
Classifier: Intended Audience :: Information Technology
Classifier: License :: OSI Approved :: MIT License
Classifier: Natural Language :: English
Classifier: Programming Language :: Python :: 2.7
Classifier: Programming Language :: Python :: 3.5
Classifier: Topic :: Software Development :: Libraries :: Python Modules
Classifier: Topic :: Software Development :: Quality Assurance
Classifier: Topic :: Software Development :: Testing
Provides-Extra: test
Provides-Extra: development
